debinterface/__init__.py
debinterface/adapter.py
debinterface/adapterValidation.py
debinterface/dnsmasqRange.py
debinterface/hostapd.py
debinterface/interfaces.py
debinterface/interfacesReader.py
debinterface/interfacesWriter.py
debinterface/toolutils.py
debinterface-3.4.0.dist-info/METADATA
debinterface-3.4.0.dist-info/RECORD
debinterface-3.4.0.dist-info/WHEEL
debinterface-3.4.0.dist-info/top_level.txt
