Metadata-Version: 2.1
Name: debinterface
Version: 3.4.0
Summary: A simple Python library for dealing with the /etc/network/interfaces file in most Debian based distributions.
Home-page: https://github.com/nMustaki/debinterface
Author: Douglas Greenbaum
Author-email: dggreenbaum@greenbad.org
Maintainer: Nathan Mustaki
Maintainer-email: feydaykyn@gmail.com
License: BSD
Download-URL: https://github.com/nMustaki/debinterface/archive/v3.4.0.zip
Keywords: debian,network,system,configuration
Platform: UNKNOWN
Classifier: Development Status :: 5 - Production/Stable
Classifier: License :: OSI Approved :: BSD License
Classifier: Development Status :: 5 - Production/Stable
Classifier: Intended Audience :: Developers
Classifier: Natural Language :: English
Classifier: Topic :: System :: Systems Administration
Classifier: Operating System :: POSIX :: Linux
Classifier: Programming Language :: Python :: 2.7
Classifier: Programming Language :: Python :: 3.5
Classifier: Programming Language :: Python :: Implementation :: CPython
Classifier: Programming Language :: Python :: Implementation :: PyPy
Provides-Extra: dev
Provides-Extra: dev
Requires-Dist: check-manifest; extra == 'dev'
Requires-Dist: twine; extra == 'dev'
